yucctools/__init__.py
yucctools/format_util.py
yucctools/hello.py
yucctools/log_util.py
yucctools/set_seed.py
yucctools-0.1.9.dist-info/METADATA
yucctools-0.1.9.dist-info/WHEEL
yucctools-0.1.9.dist-info/top_level.txt
yucctools-0.1.9.dist-info/RECORD
