Metadata-Version: 2.1
Name: yucctools
Version: 0.1.9
Summary: 一些常用的通用的工具, 比如日志记录工具
Home-page: https://github.com/yucc2018/yucctools
Author: Chen-Chen Yu
Author-email: 6506666@gmail.com
License: MIT
Platform: UNKNOWN
